dynamic_json/__init__.py
dynamic_json/json_wrappers.py
dynamic_json-1.0.3.dist-info/LICENSE.txt
dynamic_json-1.0.3.dist-info/METADATA
dynamic_json-1.0.3.dist-info/WHEEL
dynamic_json-1.0.3.dist-info/top_level.txt
dynamic_json-1.0.3.dist-info/RECORD
