Metadata-Version: 2.1
Name: dynamic-json
Version: 1.0.3
Summary: Enables self referential json entries
Home-page: https://github.com/childsish/dynamic-json
Author: Liam Childs
Author-email: liam.h.childs@gmail.com
License: MIT
Keywords: development json configuration
Platform: UNKNOWN
Classifier: Development Status :: 5 - Production/Stable
Classifier: Intended Audience :: Developers
Classifier: License :: OSI Approved :: MIT License
Classifier: Programming Language :: Python :: 3.8
Requires-Python: >=3.0
Provides-Extra: dev
Requires-Dist: twine ; extra == 'dev'
Requires-Dist: wheel ; extra == 'dev'
